setup.cfg
setup.py
lauda/__init__.py
lauda/contextmanager.py
lauda/decorators.py
lauda/stopwatch.py
lauda.egg-info/PKG-INFO
lauda.egg-info/SOURCES.txt
lauda.egg-info/dependency_links.txt
lauda.egg-info/not-zip-safe
lauda.egg-info/top_level.txt