Metadata-Version: 1.1
Name: lauda
Version: 1.1.0
Summary: A very simple python module for measuring time.
Home-page: UNKNOWN
Author: Andrea Stagi
Author-email: stagi.andrea@gmail.com
License: MIT
Keywords: time measurement
Platform: UNKNOWN
Classifier: License :: OSI Approved :: MIT License
Classifier: Natural Language :: English
Classifier: Operating System :: OS Independent
Classifier: Programming Language :: Python
Classifier: Programming Language :: Python :: 2
Classifier: Programming Language :: Python :: 2.6
Classifier: Programming Language :: Python :: 2.7
Classifier: Programming Language :: Python :: 3
Classifier: Programming Language :: Python :: 3.3
Classifier: Programming Language :: Python :: 3.4
